db_connectorXCI/.gitignore
db_connectorXCI/README.md
db_connectorXCI/__init__.py
db_connectorXCI/base_model.py
db_connectorXCI/config.ini
db_connectorXCI/configuration.py
db_connectorXCI/engine.py
db_connectorXCI/requirements.d
db_connectorXCI/test/User.py
db_connectorXCI/test/__init__.py
db_connectorXCI/test/test.py
db_connectorxci-1.dist-info/METADATA
db_connectorxci-1.dist-info/WHEEL
db_connectorxci-1.dist-info/licenses/LICENCE
db_connectorxci-1.dist-info/RECORD
