Metadata-Version: 2.1
Name: db_connectorXCI
Version: 1
Summary: Db connector
Project-URL: Homepage, https://github.com/nguacon01/db_connector.git
Project-URL: Bug Tracker, https://github.com/nguacon01/db_connector/issues
Author-email: DO Manh Dung <dungdm6191@gmail.com>
License-File: LICENCE
Classifier: License :: OSI Approved :: MIT License
Classifier: Operating System :: OS Independent
Classifier: Programming Language :: Python :: 3
Requires-Python: >=3.7
